README.md
setup.py
exchange_api/__init__.py
exchange_api/exchange.py
exchange_api.egg-info/PKG-INFO
exchange_api.egg-info/SOURCES.txt
exchange_api.egg-info/dependency_links.txt
exchange_api.egg-info/top_level.txt