Metadata-Version: 2.1
Name: exchange-api
Version: 1.0.0
Summary: A Framework for Abstracting Crypto-Currency Exchange APIs
Home-page: https://github.com/gaberust/exchange_api
Author: Cory Cline, Gabe Rust
License: LICENSE
Platform: UNKNOWN
Classifier: Programming Language :: Python :: 3
Classifier: License :: OSI Approved :: MIT License
Classifier: Operating System :: OS Independent
Requires-Python: >=3.6
